ariquantum/__init__.py
ariquantum/build_operator.py
ariquantum/exceptions.py
ariquantum/helpers.py
ariquantum/quantum_register.py
ariquantum/qubit.py
ariquantum/visualization.py
ariquantum-0.1.2.dist-info/licenses/LICENSE
ariquantum-0.1.2.dist-info/METADATA
ariquantum-0.1.2.dist-info/WHEEL
ariquantum-0.1.2.dist-info/top_level.txt
ariquantum-0.1.2.dist-info/RECORD
