Metadata-Version: 2.4
Name: ariquantum
Version: 0.1.2
Summary: Simple quantum computing simulation library
Author-email: Arim Shcherbakov <arimshcherbakov@gmail.com>
License: MIT License
Project-URL: Homepage, https://github.com/ariquantum/ariquantum
Project-URL: Issues, https://github.com/ariquantum/ariquantum/issues
Classifier: Programming Language :: Python :: 3
Classifier: License :: OSI Approved :: MIT License
Classifier: Operating System :: OS Independent
Classifier: Topic :: Scientific/Engineering :: Physics
Classifier: Intended Audience :: Education
Requires-Python: >=3.9
License-File: LICENSE
Requires-Dist: numpy>=1.20.0
Dynamic: license-file
